channel/__init__.py
channel/description.py
video/__init__.py
video/description.py
video/title.py
youtube/__init__.py
youtube_creator_cli-0.0.0.data/scripts/yt
youtube_creator_cli-0.0.0.dist-info/METADATA
youtube_creator_cli-0.0.0.dist-info/WHEEL
youtube_creator_cli-0.0.0.dist-info/top_level.txt
youtube_creator_cli-0.0.0.dist-info/RECORD
