Metadata-Version: 2.1
Name: youtube-creator-cli
Version: 0.0.0
Summary: The ultimate Youtube creator's CLI
Home-page: https://github.com/gadhagod/Youtube-Creator-CLI
Author: Aarav Borthakur
Author-email: gadhaguy13@gmail.com
License: UNKNOWN
Platform: UNKNOWN
Classifier: Programming Language :: Python :: 3
Classifier: License :: OSI Approved :: MIT License
Classifier: Operating System :: OS Independent
Requires-Python: >=3.6
Requires-Dist: click
Requires-Dist: google-api-python-client
Requires-Dist: google-auth-httplib2
Requires-Dist: google-auth-oauthlib
